Workbook

Sheet Cover
B5: GritFuel
B7: Headcount & Capacity Plan
B9: Y1 – Y3 · Quarterly · April 2026 · Internal / Investor use
B14: Bottom-up model · Capacity-driven · Brand strategist = binding constraint
B16: Assumptions | D16: All hardcoded inputs — edit here, model updates throughout
B17: Capacity Model | D17: Hours per client per tier · clients per FTE · bottleneck analysis
B18: Headcount Plan | D18: Quarterly FTE by role · Y1–Y3 · hire triggers
B19: Revenue & Cost | D19: Client ramp · blended ACV · revenue vs. cost · gross margin
B21: Colour conventions: Blue = hardcoded input · Black = formula · Green = cross-sheet link · Yellow bg = key assumption

Sheet Assumptions
B2: GritFuel — Assumptions
B4: PRICING — Monthly subscription (EUR)
B5: Core tier ACV / month | C5: 3500 | D5: EUR · no public pricing in beta
B6: Growth tier ACV / month | C6: 5250 | D6: EUR
B7: Performance tier ACV / month | C7: 8000 | D7: EUR
B8: Tier mix — Core | C8: 0.5 | D8: % of total clients
B9: Tier mix — Growth | C9: 0.35 | D9: % of total clients
B10: Tier mix — Performance | C10: 0.15 | D10: % of total clients
B12: CAPACITY — Hours per month per FTE
B13: Total working hours / month | C13: 160 | D13: Standard FTE
B14: Overhead & non-billable (%) | C14: 0.35 | D14: Admin, BD, internal
B15: Productive client hours / FTE | C15: =C13*(1-C14) -> 104 | D15: Calculated
B17: CAPACITY — Strategist hours per client per month
B18: Core — brand strategist hrs | C18: 9 | D18: Incl. prep, session, playbook, oversight
B19: Growth — brand strategist hrs | C19: 15
B20: Performance — brand strategist hrs | C20: 24
B21: Core — PM strategist hrs | C21: 2 | D21: Paid media oversight
B22: Growth — PM strategist hrs | C22: 5
B23: Performance — PM strategist hrs | C23: 9
B25: HEADCOUNT COSTS — Monthly all-in (EUR, incl. employer costs)
B26: Partner / co-founder draw — Y1 | C26: 0 | D26: Sweat equity phase
B27: Partner / co-founder draw — Y2 | C27: 4000 | D27: Modest draw from Month 13
B28: Partner / co-founder draw — Y3 | C28: 6000
B29: Brand Strategist — NL / core | C29: 5500 | D29: All-in monthly cost
B30: Brand Strategist — SA contractor | C30: 3000 | D30: Favourable FX vs. EUR
B31: PM Strategist — primary | C31: 8000 | D31: NL-based all-in
B32: PM Strategist — additional | C32: 6000 | D32: SA/remote
B33: Client Success Manager | C33: 5500 | D33: NL or remote
B34: Tech Lead | C34: 6000 | D34: Remote/Morocco adjacent
B35: SSA Market Lead | C35: 3500 | D35: Lagos or Nairobi
B36: CTO / Head of Product | C36: 12000 | D36: NL-based or remote senior
B37: Head of Operations | C37: 7000
B38: AI Expert (part-time advisory) | C38: 1500 | D38: Per expert, 2 in circle

Sheet Capacity Model
B2: Capacity Model — Hours & Client Throughput
B4: Hours per client / month (by tier) | C4: Core | D4: Growth | E4: Performance | F4: Weighted avg
B5: Brand Strategist | C5: =Assumptions!C18 -> 9 | D5: =Assumptions!C19 -> 15 | E5: =Assumptions!C20 -> 24 | F5: =C5*Assumptions!C8+D5*Assumptions!C9+E5*Assumptions!C10 -> 13.35
B6: PM Strategist | C6: =Assumptions!C21 -> 2 | D6: =Assumptions!C22 -> 5 | E6: =Assumptions!C23 -> 9 | F6: =C6*Assumptions!C8+D6*Assumptions!C9+E6*Assumptions!C10 -> 4.1
B8: Productive hours / FTE / month | C8: =Assumptions!C15 -> 104
B10: Max clients per FTE (productive hrs ÷ weighted avg hrs) | C10: Brand Strat | D10: PM Strat
B11: Theoretical maximum | C11: =Assumptions!C15/F5 -> 7.7902622 | D11: =Assumptions!C15/F6 -> 25.365854
B12: Planning target (80% of max — realistic with ramp-up) | C12: =INT(C11*0.8) -> 6 | D12: =INT(D11*0.8) -> 20
B14: ⚠ Brand Strategist = binding constraint. PM Strategist capacity is ~2-3× higher — PM headcount follows brand strategist growth, not the other way around.

Sheet Headcount Plan
B2: Headcount Plan — Quarterly FTE / Contractor Count (Y1–Y3)
B4: Role | C4: Q1 Y1 | D4: Q2 Y1 | E4: Q3 Y1 | F4: Q4 Y1 | G4: Q1 Y2 | H4: Q2 Y2 | I4: Q3 Y2 | J4: Q4 Y2 | K4: Q1 Y3 | L4: Q2 Y3 | M4: Q3 Y3 | N4: Q4 Y3
B5: FOUNDERS / CORE TEAM
B6: Brand Strategist (co-founder ×2) | C6: 2 | D6: 2 | E6: 2 | F6: 2 | G6: 2 | H6: 2 | I6: 2 | J6: 2 | K6: 2 | L6: 2 | M6: 2 | N6: 2
B7: PM Strategist (co-founder ×1) | C7: 1 | D7: 1 | E7: 1 | F7: 1 | G7: 1 | H7: 1 | I7: 1 | J7: 1 | K7: 1 | L7: 1 | M7: 1 | N7: 1
B8: Activation Expert (co-founder ×1) | C8: 1 | D8: 1 | E8: 1 | F8: 1 | G8: 1 | H8: 1 | I8: 1 | J8: 1 | K8: 1 | L8: 1 | M8: 1 | N8: 1
B9: Brand Strategist — core (non-founder) | C9: 1 | D9: 1 | E9: 1 | F9: 1 | G9: 1 | H9: 1 | I9: 1 | J9: 1 | K9: 1 | L9: 1 | M9: 1 | N9: 1
B10: AI Expert (part-time advisory ×2) | C10: 2 | D10: 2 | E10: 2 | F10: 2 | G10: 2 | H10: 2 | I10: 2 | J10: 2 | K10: 2 | L10: 2 | M10: 2 | N10: 2
B12: NEW HIRES & FORMALISED POOL (cumulative additional FTEs)
B13: Client Success / Ops Manager | C13: 0 | D13: 0 | E13: 0 | F13: 1 | G13: 1 | H13: 1 | I13: 1 | J13: 1 | K13: 1 | L13: 1 | M13: 1 | N13: 1
B14: Brand Strategist — SA pool (formalised) | C14: 0 | D14: 0 | E14: 0 | F14: 0 | G14: 1 | H14: 1 | I14: 2 | J14: 2 | K14: 3 | L14: 4 | M14: 5 | N14: 5
B15: PM Strategist — additional | C15: 0 | D15: 0 | E15: 0 | F15: 0 | G15: 0 | H15: 0 | I15: 0 | J15: 1 | K15: 1 | L15: 1 | M15: 2 | N15: 2
B16: Tech Lead (Brandformance OS build) | C16: 0 | D16: 0 | E16: 0 | F16: 1 | G16: 1 | H16: 1 | I16: 1 | J16: 1 | K16: 1 | L16: 1 | M16: 1 | N16: 1
B17: SSA Market Lead (Lagos or Nairobi) | C17: 0 | D17: 0 | E17: 0 | F17: 0 | G17: 0 | H17: 0 | I17: 1 | J17: 1 | K17: 1 | L17: 1 | M17: 1 | N17: 1
B18: Business Dev / Sales | C18: 0 | D18: 0 | E18: 0 | F18: 0 | G18: 0 | H18: 0 | I18: 0 | J18: 1 | K18: 1 | L18: 1 | M18: 1 | N18: 1
B19: CTO / Head of Product | C19: 0 | D19: 0 | E19: 0 | F19: 0 | G19: 0 | H19: 0 | I19: 0 | J19: 0 | K19: 1 | L19: 1 | M19: 1 | N19: 1
B20: Head of Operations | C20: 0 | D20: 0 | E20: 0 | F20: 0 | G20: 0 | H20: 0 | I20: 0 | J20: 0 | K20: 0 | L20: 1 | M20: 1 | N20: 1
B22: TOTALS
B23: Total Brand Strategists | C23: 3 | D23: 3 | E23: 3 | F23: 3 | G23: 4 | H23: 4 | I23: 5 | J23: 5 | K23: 6 | L23: 7 | M23: 8 | N23: 8
B24: Total PM Strategists | C24: 1 | D24: 1 | E24: 1 | F24: 1 | G24: 1 | H24: 1 | I24: 1 | J24: 2 | K24: 2 | L24: 2 | M24: 3 | N24: 3
B25: Total FTE (all roles) | C25: 7 | D25: 7 | E25: 8 | F25: 9 | G25: 10 | H25: 10 | I25: 12 | J25: 14 | K25: 16 | L25: 18 | M25: 19 | N25: 19
B27: Key hire triggers:
B28: Q4 Y1 — Tech Lead + Client Success Mgr | C28: Platform build starts; 9 clients — admin overhead a constraint
B29: Q1 Y2 — SA Brand Strategist (1st) | C29: Approaching 12 clients; 3 strats at capacity limit — SA pool begins
B30: Q3 Y2 — SA Brand Strat (2nd) + SSA Lead | C30: 18 clients; SSA presence now justified — Lagos or Nairobi base
B31: Q4 Y2 — PM additional + Biz Dev | C31: 21 clients; paid media volume & inbound now require dedicated sales
B32: Q1 Y3 — SA Brand Strat (3rd) + CTO | C32: 26 clients; Brandformance OS automation phase requires senior tech
B33: Q2 Y3 — SA Brand Strat (4th) + Head of Ops | C33: 32 clients; operational complexity requires dedicated Ops lead

Sheet Revenue & Cost
B2: Revenue & Cost Projection — Quarterly (Y1–Y3)
B4: Metric (EUR) | C4: Q1 Y1 | D4: Q2 Y1 | E4: Q3 Y1 | F4: Q4 Y1 | G4: Q1 Y2 | H4: Q2 Y2 | I4: Q3 Y2 | J4: Q4 Y2 | K4: Q1 Y3 | L4: Q2 Y3 | M4: Q3 Y3 | N4: Q4 Y3
B5: CLIENTS
B6: Total active clients (end of quarter) | C6: 2 | D6: 4 | E6: 6 | F6: 9 | G6: 12 | H6: 15 | I6: 18 | J6: 21 | K6: 26 | L6: 32 | M6: 40 | N6: 48
B7: — EU clients | C7: 2 | D7: 4 | E7: 5 | F7: 7 | G7: 10 | H7: 13 | I7: 16 | J7: 19 | K7: 23 | L7: 28 | M7: 35 | N7: 42
B8: — SSA & EU→Africa clients | C8: 0 | D8: 0 | E8: 1 | F8: 2 | G8: 2 | H8: 2 | I8: 2 | J8: 2 | K8: 3 | L8: 4 | M8: 5 | N8: 6
B10: REVENUE
B11: Blended ACV / month (EUR) | C11: =Assumptions!C5*Assumptions!C8+Assumptions!C6*Assumptions!C9+Assumptions!C7*Assumptions!C10 -> 4787.5 | D11: =Assumptions!C5*Assumptions!C8+Assumptions!C6*Assumptions!C9+Assumptions!C7*Assumptions!C10 -> 4787.5 | E11: =Assumptions!C5*Assumptions!C8+Assumptions!C6*Assumptions!C9+Assumptions!C7*Assumptions!C10 -> 4787.5 | F11: =Assumptions!C5*Assumptions!C8+Assumptions!C6*Assumptions!C9+Assumptions!C7*Assumptions!C10 -> 4787.5 | G11: =Assumptions!C5*Assumptions!C8+Assumptions!C6*Assumptions!C9+Assumptions!C7*Assumptions!C10 -> 4787.5 | H11: =Assumptions!C5*Assumptions!C8+Assumptions!C6*Assumptions!C9+Assumptions!C7*Assumptions!C10 -> 4787.5 | I11: =Assumptions!C5*Assumptions!C8+Assumptions!C6*Assumptions!C9+Assumptions!C7*Assumptions!C10 -> 4787.5 | J11: =Assumptions!C5*Assumptions!C8+Assumptions!C6*Assumptions!C9+Assumptions!C7*Assumptions!C10 -> 4787.5 | K11: =Assumptions!C5*Assumptions!C8+Assumptions!C6*Assumptions!C9+Assumptions!C7*Assumptions!C10 -> 4787.5 | L11: =Assumptions!C5*Assumptions!C8+Assumptions!C6*Assumptions!C9+Assumptions!C7*Assumptions!C10 -> 4787.5 | M11: =Assumptions!C5*Assumptions!C8+Assumptions!C6*Assumptions!C9+Assumptions!C7*Assumptions!C10 -> 4787.5 | N11: =Assumptions!C5*Assumptions!C8+Assumptions!C6*Assumptions!C9+Assumptions!C7*Assumptions!C10 -> 4787.5
B12: MRR at quarter-end (EUR) | C12: =C6*C11 -> 9575 | D12: =D6*D11 -> 19150 | E12: =E6*E11 -> 28725 | F12: =F6*F11 -> 43087.5 | G12: =G6*G11 -> 57450 | H12: =H6*H11 -> 71812.5 | I12: =I6*I11 -> 86175 | J12: =J6*J11 -> 100537.5 | ... N12: =N6*N11 -> 229800
B13: Quarterly Revenue (MRR × 3) | C13: =C12*3 -> 28725 | D13: =D12*3 -> 57450 | E13: =E12*3 -> 86175 | F13: =F12*3 -> 129262.5 | G13: =G12*3 -> 172350 | H13: =H12*3 -> 215437.5 | I13: =I12*3 -> 258525 | J13: =J12*3 -> 301612.5 | ... N13: =N12*3 -> 689400
B14: ARR (implied, MRR × 12) | C14: =C12*12 -> 114900 | D14: =D12*12 -> 229800 | E14: =E12*12 -> 344700 | F14: =F12*12 -> 517050 | G14: =G12*12 -> 689400 | H14: =H12*12 -> 861750 | I14: =I12*12 -> 1034100 | J14: =J12*12 -> 1206450 | ... N14: =N12*12 -> 2757600
B16: HEADCOUNT COSTS (monthly, EUR)
B17: Partner draws (3 partners) | C17: 0 | D17: 0 | E17: 0 | F17: 0 | G17: 12000 | H17: 12000 | I17: 12000 | J17: 12000 | K17: 18000 | L17: 18000 | M17: 18000 | N17: 18000
B18: Brand Strategists — total monthly cost | C18: 5500 | D18: 5500 | E18: 5500 | F18: 5500 | G18: 8500 | H18: 8500 | I18: 11500 | J18: 11500 | K18: 14500 | L18: 17500 | M18: 20500 | N18: 20500
B19: PM Strategists — total monthly cost | C19: 8000 | D19: 8000 | E19: 8000 | F19: 8000 | G19: 8000 | H19: 8000 | I19: 8000 | J19: 14000 | K19: 14000 | L19: 14000 | M19: 20000 | N19: 20000
B20: Client Success Manager | C20: 0 | D20: 0 | E20: 0 | F20: 5500 | G20: 5500 | H20: 5500 | I20: 5500 | J20: 5500 | K20: 5500 | L20: 5500 | M20: 5500 | N20: 5500
B21: Tech Lead | C21: 0 | D21: 0 | E21: 0 | F21: 6000 | G21: 6000 | H21: 6000 | I21: 6000 | J21: 6000 | K21: 6000 | L21: 6000 | M21: 6000 | N21: 6000
B22: SSA Market Lead | C22: 0 | D22: 0 | E22: 0 | F22: 0 | G22: 0 | H22: 0 | I22: 3500 | J22: 3500 | K22: 3500 | L22: 3500 | M22: 3500 | N22: 3500
B23: Business Dev / Sales | C23: 0 | D23: 0 | E23: 0 | F23: 0 | G23: 0 | H23: 0 | I23: 0 | J23: 5500 | K23: 5500 | L23: 5500 | M23: 5500 | N23: 5500
B24: CTO / Head of Product | C24: 0 | D24: 0 | E24: 0 | F24: 0 | G24: 0 | H24: 0 | I24: 0 | J24: 0 | K24: 12000 | L24: 12000 | M24: 12000 | N24: 12000
B25: Head of Operations | C25: 0 | D25: 0 | E25: 0 | F25: 0 | G25: 0 | H25: 0 | I25: 0 | J25: 0 | K25: 0 | L25: 7000 | M25: 7000 | N25: 7000
B26: AI Experts (2 × part-time) | C26: 3000 | D26: 3000 | E26: 3000 | F26: 3000 | G26: 3000 | H26: 3000 | I26: 3000 | J26: 3000 | K26: 3000 | L26: 3000 | M26: 3000 | N26: 3000
B27: Total monthly headcount cost | C27: =C17+C18+C19+C20+C21+C22+C23+C24+C25+C26 -> 16500 | D27: =D17+D18+D19+D20+D21+D22+D23+D24+D25+D26 -> 16500 | E27: =E17+E18+E19+E20+E21+E22+E23+E24+E25+E26 -> 16500 | F27: =F17+F18+F19+F20+F21+F22+F23+F24+F25+F26 -> 28000 | G27: =G17+G18+G19+G20+G21+G22+G23+G24+G25+G26 -> 43000 | H27: =H17+H18+H19+H20+H21+H22+H23+H24+H25+H26 -> 43000 | I27: =I17+I18+I19+I20+I21+I22+I23+I24+I25+I26 -> 49500 | J27: =J17+J18+J19+J20+J21+J22+J23+J24+J25+J26 -> 61000 | ... N27: =N17+N18+N19+N20+N21+N22+N23+N24+N25+N26 -> 101000
B29: MARGIN
B30: Monthly gross margin (MRR - headcount cost) | C30: =C12-C27 -> -6925 | D30: =D12-D27 -> 2650 | E30: =E12-E27 -> 12225 | F30: =F12-F27 -> 15087.5 | G30: =G12-G27 -> 14450 | H30: =H12-H27 -> 28812.5 | I30: =I12-I27 -> 36675 | J30: =J12-J27 -> 39537.5 | ... N30: =N12-N27 -> 128800
B31: Gross margin % | C31: =IFERROR(C30/C12,"-") -> -0.7232376 | D31: =IFERROR(D30/D12,"-") -> 0.1383812 | E31: =IFERROR(E30/E12,"-") -> 0.42558747 | F31: =IFERROR(F30/F12,"-") -> 0.35015956 | G31: =IFERROR(G30/G12,"-") -> 0.25152306 | H31: =IFERROR(H30/H12,"-") -> 0.40121845 | I31: =IFERROR(I30/I12,"-") -> 0.42558747 | J31: =IFERROR(J30/J12,"-") -> 0.39326122 | ... N31: =IFERROR(N30/N12,"-") -> 0.56048738
B33: Note: Costs shown are headcount only. Add ~15–20% for tools, software, office, and travel. Credit execution costs (partner delivery via .frank / Bluegyfu) are client-funded — not reflected here as they are offset by credit revenue.
