Workbook

Sheet Cost Model
A1: GritFuel · Fixed Item Cost Model — Hybrid Scenario
A2: Price increases applied · Selected deliverables reclassified as credit-funded · All figures EUR/month
A4: RATE ASSUMPTIONS | F4: Always included (fixed delivery cost)
A5: Resource | B5: Rate (€/hr) | D5: Note | F5: Reclassified → credit-funded (removed from fixed cost)
A6: Strategist (lead / CMO-level) | B6: 120 | D6: Client-facing sessions, playbook, strategic oversight | F6: Specialist coordination
A7: Other (ops / junior / data) | B7: 80 | D7: Dashboard updates, engine runs, specialist coordination | F7: Yellow = key assumption / input
A8: CORE · €3,500/month · 70 credits [UNCHANGED] | F8: GROWTH · €5,250/month · 110 credits [+€250] | K8: PERFORMANCE · €8,000/month · 180 credits [+€500]
A9: Fixed Item | B9: Resource | C9: Hrs | D9: Cost (€) | F9: Fixed Item | G9: Resource | H9: Hrs | I9: Cost (€) | K9: Fixed Item | L9: Resource | M9: Hrs | N9: Cost (€)
A10: Monthly strategy session (1 × 60 min) | B10: Strategist | C10: 1 | D10: =C10*$B$6 -> 120 | F10: Bi-weekly alignment (2 × 60 min) | G10: Strategist | H10: 2 | I10: =H10*$B$6 -> 240 | K10: Weekly growth review (4 × 60 min) | L10: Strategist | M10: 4 | N10: =M10*$B$6 -> 480
A11: On-demand support (1.5 hrs/month) | B11: Strategist | C11: 1.5 | D11: =C11*$B$6 -> 180 | F11: On-demand support (3 hrs/month) | G11: Strategist | H11: 3 | I11: =H11*$B$6 -> 360 | K11: On-demand support (6 hrs/month) | L11: Strategist | M11: 6 | N11: =M11*$B$6 -> 720
A12: Monthly Growth Playbook (prep + write-up) | B12: Strategist | C12: 2.5 | D12: =C12*$B$6 -> 300 | F12: Monthly Growth Playbook (prep + write-up) | G12: Strategist | H12: 2.5 | I12: =H12*$B$6 -> 300 | K12: Monthly Growth Playbook (prep + write-up) | L12: Strategist | M12: 2.5 | N12: =M12*$B$6 -> 300
A13: Live growth dashboard (monthly update) | B13: Other | C13: 1 | D13: =C13*$B$7 -> 80 | F13: Live growth dashboard (monthly update) | G13: Other | H13: 1 | I13: =H13*$B$7 -> 80 | K13: Live growth dashboard (monthly update) | L13: Other | M13: 1 | N13: =M13*$B$7 -> 80
A14: Compounding engine (run + review) | B14: Other | C14: 0.5 | D14: =C14*$B$7 -> 40 | F14: Compounding engine (run + review) | G14: Other | H14: 0.5 | I14: =H14*$B$7 -> 40 | K14: Compounding engine (run + review) | L14: Other | M14: 0.5 | N14: =M14*$B$7 -> 40
A15: Ongoing brand & messaging guidance | B15: Strategist | C15: 0.5 | D15: =C15*$B$6 -> 60 | F15: Ongoing brand & messaging guidance | G15: Strategist | H15: 0.5 | I15: =H15*$B$6 -> 60 | K15: Ongoing brand & messaging guidance | L15: Strategist | M15: 0.5 | N15: =M15*$B$6 -> 60
A16: Specialist coordination (back-end routing) | B16: Other | C16: 0.5 | D16: =C16*$B$7 -> 40 | F16: Fractional CMO oversight | G16: Strategist | H16: 2 | I16: =H16*$B$6 -> 240 | K16: Fractional CMO oversight | L16: Strategist | M16: 2 | N16: =M16*$B$6 -> 240
A17: Session time cost | D17: =SUM(D10,D11) -> 300 | F17: ⇢ Structured growth experiments | G17: Strategist | H17: 1.5 | I17: =H17*$B$6 -> 180 | K17: ⇢ Senior strategic intensity | L17: Strategist | M17: 2 | N17: =M17*$B$6 -> 240
A18: Other fixed item cost | D18: =SUM(D12,D13,D14,D15) -> 480 | F18: ⇢ Multi-channel orchestration (3+ channels) | G18: Strategist | H18: 1.5 | I18: =H18*$B$6 -> 180 | K18: ⇢ Advanced testing architecture | L18: Strategist | M18: 1.5 | N18: =M18*$B$6 -> 180
A19: Specialist coordination | D19: =SUM(D16) -> 40 | F19: Direct specialist briefing (brand + perf) | G19: Other | H19: 1 | I19: =H19*$B$7 -> 80 | K19: ⇢ Forecasting & growth modelling | L19: Strategist | M19: 2 | N19: =M19*$B$6 -> 240
A20: ⇢ Reclassified (credit-funded, not in fixed) | D20: 0 | F20: Session time cost | I20: =SUM(I10,I11) -> 600 | K20: Direct specialist briefing (brand+perf+events) | L20: Other | M20: 1.5 | N20: =M20*$B$7 -> 120
A21: TOTAL FIXED DELIVERY COST | D21: =D17+D18+D19 -> 820 | F21: Other fixed item cost | I21: =SUM(I12,I13,I14,I15,I16) -> 720 | K21: Session time cost | N21: =SUM(N10,N11) -> 1200
F22: Specialist coordination | I22: =SUM(I19) -> 80 | K22: Other fixed item cost | N22: =SUM(N12,N13,N14,N15,N16) -> 720
A23: COMMERCIAL SUMMARY | F23: ⇢ Reclassified (credit-funded, not in fixed) | I23: =SUM(I17,I18) -> 360 | K23: Specialist coordination | N23: =SUM(N20) -> 120
A24: Subscription revenue | D24: 3500 | F24: TOTAL FIXED DELIVERY COST | I24: =I20+I21+I22 -> 1400 | K24: ⇢ Reclassified (credit-funded, not in fixed) | N24: =SUM(N17,N18,N19) -> 660
A25: — Credit pool value | D25: 1750 | K25: TOTAL FIXED DELIVERY COST | N25: =N21+N22+N23 -> 2040
A26: — Fixed item revenue | D26: 1750 | F26: COMMERCIAL SUMMARY
A27: Fixed delivery cost | D27: =D21 -> 820 | F27: Subscription revenue | I27: 5250 | K27: COMMERCIAL SUMMARY
A28: Gross margin (€) | D28: =D26-D27 -> 930 | F28: — Credit pool value | I28: 2750 | K28: Subscription revenue | N28: 8000
A29: Gross margin (%) | D29: =IF(D26=0,0,D28/D26) -> 0.53142857 | F29: — Fixed item revenue | I29: 2500 | K29: — Credit pool value | N29: 4500
F30: Fixed delivery cost | I30: =I24 -> 1400 | K30: — Fixed item revenue | N30: 3500
F31: Gross margin (€) | I31: =I29-I30 -> 1100 | K31: Fixed delivery cost | N31: =N25 -> 2040
F32: Gross margin (%) | I32: =IF(I29=0,0,I31/I29) -> 0.44 | K32: Gross margin (€) | N32: =N30-N31 -> 1460
K33: Gross margin (%) | N33: =IF(N30=0,0,N32/N30) -> 0.41714286

Sheet Summary
A1: GritFuel · Hybrid Scenario — Commercial Summary
A2: Strategist €120/hr · Other €80/hr · Reclassified items shown separately
B4: Core | C4: Growth | D4: Performance
A5: REVENUE
A6: Subscription revenue (total) | B6: ='Cost Model'!D24 -> 3500 | C6: ='Cost Model'!I27 -> 5250 | D6: ='Cost Model'!N28 -> 8000
A7: — Credit pool value | B7: ='Cost Model'!D25 -> 1750 | C7: ='Cost Model'!I28 -> 2750 | D7: ='Cost Model'!N29 -> 4500
A8: — Fixed item revenue | B8: ='Cost Model'!D26 -> 1750 | C8: ='Cost Model'!I29 -> 2500 | D8: ='Cost Model'!N30 -> 3500
A9: Credits included | B9: 70 | C9: 110 | D9: 180
A10: COST BREAKDOWN
A11: Session time cost | B11: ='Cost Model'!D17 -> 300 | C11: ='Cost Model'!I20 -> 600 | D11: ='Cost Model'!N21 -> 1200
A12: Other fixed item cost | B12: ='Cost Model'!D18 -> 480 | C12: ='Cost Model'!I21 -> 720 | D12: ='Cost Model'!N22 -> 720
A13: Specialist coordination | B13: ='Cost Model'!D19 -> 40 | C13: ='Cost Model'!I22 -> 80 | D13: ='Cost Model'!N23 -> 120
A14: Reclassified → credit-funded | B14: ='Cost Model'!D20 -> 0 | C14: ='Cost Model'!I23 -> 360 | D14: ='Cost Model'!N24 -> 660
A15: Total fixed delivery cost | B15: ='Cost Model'!D27 -> 820 | C15: ='Cost Model'!I30 -> 1400 | D15: ='Cost Model'!N31 -> 2040
A16: MARGIN
A17: Gross margin (€) | B17: ='Cost Model'!D28 -> 930 | C17: ='Cost Model'!I31 -> 1100 | D17: ='Cost Model'!N32 -> 1460
A18: Gross margin (%) | B18: ='Cost Model'!D29 -> 0.53142857 | C18: ='Cost Model'!I32 -> 0.44 | D18: ='Cost Model'!N33 -> 0.41714286
A19: HOURS
A20: Total hrs/month (fixed items) | B20: =SUM('Cost Model'!C10:C16) -> 7.5 | C20: =SUM('Cost Model'!H10:H19) -> 15.5 | D20: =SUM('Cost Model'!M10:M20) -> 23.5
A22: Note: 'Reclassified → credit-funded' items are still delivered for clients but funded from the credit pool, not the fixed subscription cost. They appear here for transparency — this cost is covered by credit margin, not shown in this model. Blue = adjustable input. Yellow = key commercial assumption.
